mikedoc/__init__.py
mikedoc/__main__.py
mikedoc/browser/__init__.py
mikedoc/builder/__init__.py
mikedoc/cli/__init__.py
mikedoc/errors/__init__.py
mikedoc/misc/__init__.py
mikedoc/templates/__init__.py
tests/__init__.py
tests/__pycache__/__init__.cpython-38.pyc
tests/project/__init__.py
tests/project/__main__.py
tests/project/package1/__init__.py
tests/project/package1/module1.py
tests/project/package2/__init__.py
tests/project/package2/module2.py
mikedoc-0.0.7.dist-info/LICENSE
mikedoc-0.0.7.dist-info/METADATA
mikedoc-0.0.7.dist-info/WHEEL
mikedoc-0.0.7.dist-info/entry_points.txt
mikedoc-0.0.7.dist-info/top_level.txt
mikedoc-0.0.7.dist-info/RECORD
